pydantic_xmlmodel/__init__.py
pydantic_xmlmodel/py.typed
pydantic_xmlmodel/serde.py
pydantic_xmlmodel/xmlmodel.py
pydantic_xmlmodel-0.4.dist-info/LICENSE
pydantic_xmlmodel-0.4.dist-info/METADATA
pydantic_xmlmodel-0.4.dist-info/WHEEL
pydantic_xmlmodel-0.4.dist-info/RECORD
