Metadata-Version: 2.1
Name: pydantic-xmlmodel
Version: 0.4
Summary: PydanticXML is a Python library that provides a way to convert Pydantic models to XML and vice versa.
Home-page: https://github.com/cofob/pydanticxml
License: MIT
Author: cofob
Author-email: cofob@riseup.net
Requires-Python: >=3.8.1,<4.0
Classifier: License :: OSI Approved :: MIT License
Classifier: Programming Language :: Python :: 3
Classifier: Programming Language :: Python :: 3.9
Classifier: Programming Language :: Python :: 3.10
Classifier: Programming Language :: Python :: 3.11
Classifier: Programming Language :: Python :: 3.12
Requires-Dist: pydantic (>=2,<3)
Project-URL: Repository, https://github.com/cofob/pydanticxml
